odoo/addons/stock_barcodes_move_location/README.rst
odoo/addons/stock_barcodes_move_location/__init__.py
odoo/addons/stock_barcodes_move_location/__manifest__.py
odoo/addons/stock_barcodes_move_location/i18n/stock_barcodes_move_location.pot
odoo/addons/stock_barcodes_move_location/readme/CONTRIBUTORS.rst
odoo/addons/stock_barcodes_move_location/readme/DESCRIPTION.rst
odoo/addons/stock_barcodes_move_location/readme/USAGE.rst
odoo/addons/stock_barcodes_move_location/static/description/icon.png
odoo/addons/stock_barcodes_move_location/static/description/index.html
odoo/addons/stock_barcodes_move_location/static/src/img/scan.png
odoo/addons/stock_barcodes_move_location/static/src/js/stock_barcodes.js
odoo/addons/stock_barcodes_move_location/views/assets.xml
odoo/addons/stock_barcodes_move_location/wizard/__init__.py
odoo/addons/stock_barcodes_move_location/wizard/stock_barcodes_read_move_location.py
odoo/addons/stock_barcodes_move_location/wizard/stock_barcodes_read_move_location_views.xml
odoo/addons/stock_barcodes_move_location/wizard/stock_move_location.py
odoo/addons/stock_barcodes_move_location/wizard/stock_move_location_views.xml
odoo11_addon_stock_barcodes_move_location-11.0.1.0.0.99.dev4.dist-info/METADATA
odoo11_addon_stock_barcodes_move_location-11.0.1.0.0.99.dev4.dist-info/WHEEL
odoo11_addon_stock_barcodes_move_location-11.0.1.0.0.99.dev4.dist-info/top_level.txt
odoo11_addon_stock_barcodes_move_location-11.0.1.0.0.99.dev4.dist-info/RECORD
